{
  "movies": [
    {
      "cast": [
        {
          "name": "Neo",
          "star": "Keanu Reeves"
        },
        {
          "name": "Morpheus",
          "star": "Laurence Fishburne"
        },
        {
          "name": "Trinity",
          "star": "Carrie-Anne Moss"
        },
        {
          "name": "Agent Smith",
          "star": "Hugo Weaving"
        }
      ],
      "directors": [
        "Lana Wachowski",
        "Lilly Wachowski"
      ],
      "id": 11001,
      "length": 196,
      "title": "The Matrix",
      "writers": [
        "Lana Wachowski",
        "Lilly Wachowski"
      ],
      "year": 1999
    },
    {
      "cast": [
        {
          "name": "Forrest Gump",
          "star": "Tom Hanks"
        },
        {
          "name": "Mrs. Gump",
          "star": "Sally Field"
        },
        {
          "name": "Jenny Curran",
          "star": "Robin Wright"
        },
        {
          "name": "Bubba Blue",
          "star": "Mykelti Williamson"
        }
      ],
      "directors": [
        "Robert Zemeckis"
      ],
      "id": 9871,
      "length": 202,
      "title": "Forrest Gump",
      "writers": [
        "Winston Groom",
        "Eric Roth"
      ],
      "year": 1994
    }
  ]
}
